manoelgadi12
