Metadata-Version: 1.1
Name: manoelgadi12
Version: 1.111
Summary: porject helps to automatically or with human assistance manipulate data
Home-page: https://github.com/ersh24/manoelgadi12
Author: ersh
Author-email: ershov@student.ie.edu
License: MIT license
Keywords: manoelgadi12
Platform: UNKNOWN
Classifier: Development Status :: 2 - Pre-Alpha
Classifier: Intended Audience :: Developers
Classifier: License :: OSI Approved :: MIT License
Classifier: Natural Language :: English
Classifier: Programming Language :: Python :: 2
Classifier: Programming Language :: Python :: 2.6
Classifier: Programming Language :: Python :: 2.7
Classifier: Programming Language :: Python :: 3
Classifier: Programming Language :: Python :: 3.3
Classifier: Programming Language :: Python :: 3.4
Classifier: Programming Language :: Python :: 3.5
